Workbook

Sheet Formula Fundamentals
B1: Chocolate Chip | C1: Oatmeal Raisin | D1: Sugar Cookie | E1: Totals | G1: Tax Rate
A2: Revenue | B2: 10 | C2: 8 | D2: 5 | E2: =B2+C2+D2 -> 23 | G2: 0.1
A3: Cost | B3: 4 | C3: 3 | D3: 2 | E3: =B3+C3+D3 -> 9
A4: Profit | B4: =B2-B3 -> 6 | C4: =C2-C3 -> 5 | D4: =D2-D3 -> 3 | E4: =E2-E3 -> 14
A5: Tax | B5: =B4*'Tax Rate'!$A$2 -> 0.6 | C5: =C4*'Tax Rate'!$A$2 -> 0.5 | D5: =D4*'Tax Rate'!$A$2 -> 0.3 | E5: =E4*'Tax Rate'!$A$2 -> 1.4
A9: Profit Split | B9: =E4/2 -> 7

Sheet Tax Rate
A1: Tax Rate
A2: 0.1 | E2: =B2+C2+D2 -> 0
E3: =B3+C3+D3 -> 0
B4: =B2-B3 -> 0 | C4: =C2-C3 -> 0 | D4: =D2-D3 -> 0 | E4: =E2-E3 -> 0
B5: =B4*'Tax Rate'!$A$2 -> 0 | C5: =C4*'Tax Rate'!$A$2 -> 0 | D5: =D4*'Tax Rate'!$A$2 -> 0 | E5: =E4*'Tax Rate'!$A$2 -> 0
B9: =E4/2 -> 0

Sheet Order of Operations
B1: Chocolate Chip | D1: Tax Rate
A2: Revenue | B2: 10 | D2: 0.1
A3: Cost | B3: 4
A4: Profit | B4: =B2-B3 -> 6
A5: Tax | B5: =(B2-B3)*D2 -> 0.6
A7: * and / evaluated first
A8: + and - evaluated second
A9: Use parentheses to control the order

Sheet Basic Functions
A1: Cookie Name | B1: Cookies Sold
A2: Chocolate Chip | B2: 97 | D2: How many cookies sold? | E2: =SUM(B2:B8) -> 421
A3: Oatmeal Raisin | B3: 77 | D3: Most # of cookies sold | E3: =MAX(B2:B8) -> 97
A4: Sugar Cookie | B4: 67 | D4: Least # of cookies sold | E4: =MIN(B2:B8) -> 36
A5: Snickerdoodle | B5: 52 | D5: 2nd most sold | E5: =LARGE(B2:B8, 2) -> 77
A6: Birthday Cake | B6: 52 | D6: 2nd least sold | E6: =SMALL(B2:B8, 2) -> 40
A7: Peanut Butter | B7: 40 | D7: # of cookies with sales? | E7: =COUNT(B2:B8) -> 7
A8: Fortune | B8: 36
D10: Average sold? | E10: =AVERAGE(B2:B8) -> 60.142857
D11: What # is in the middle? | E11: =MEDIAN(B2:B8) -> 52
D12: What # occurs most frequently? | E12: =MODE(B2:B8) -> 52

Sheet Conditional Functions
A1: Cookie Name | B1: Country | C1: Cookies Sold
A2: Chocolate Chip | B2: United States | C2: 28 | E2: Sumif | F2: =SUMIF(B:B,B2,C:C) -> 362
A3: Oatmeal Raisin | B3: United States | C3: 32 | E3: sumifs | F3: {=SUM(SUMIFS(C:C,B:B,B2,A:A,A2:A3))} -> 60
A4: Sugar Cookie | B4: United States | C4: 52
A5: Snickerdoodle | B5: United States | C5: 67
A6: Birthday Cake | B6: United States | C6: 44
A7: Peanut Butter | B7: United States | C7: 39 | E7: Averageif | F7: =AVERAGEIF(B:B, B2, C:C) -> 51.714286
A8: Fortune | B8: United States | C8: 100 | E8: Averageifs | F8: {=SUM(AVERAGEIFS(C:C,B:B,B2,A:A,A2:A3))} -> 60
A9: Chocolate Chip | B9: India | C9: 75 | E9: Countif | F9: =COUNTIF(B:B, B9) -> 7
A10: Oatmeal Raisin | B10: India | C10: 32 | E10: Countifs | F10: {=SUM(COUNTIFS(B:B, B9, A:A, A9:A10))} -> 2
A11: Sugar Cookie | B11: India | C11: 40 | E11: Minifs | F11: =_xlfn.MINIFS(C:C,B:B,B16,A:A,A17) -> 41
A12: Snickerdoodle | B12: India | C12: 21 | E12: Maxifs | F12: =_xlfn.MAXIFS(C:C, B:B, B16, A:A, A18) -> 92
A13: Birthday Cake | B13: India | C13: 58
A14: Peanut Butter | B14: India | C14: 21
A15: Fortune | B15: India | C15: 54
A16: Chocolate Chip | B16: Philippines | C16: 55
A17: Oatmeal Raisin | B17: Philippines | C17: 41
A18: Sugar Cookie | B18: Philippines | C18: 92
A19: Snickerdoodle | B19: Philippines | C19: 89
A20: Birthday Cake | B20: Philippines | C20: 34
A21: Peanut Butter | B21: Philippines | C21: 29
A22: Fortune | B22: Philippines | C22: 100

Sheet Text Functions
A1: Proper
A2: kevin cookie company
A3: =PROPER(A2) -> Kevin Cookie Company
A5: Trim
A6: Kevin Cookie Company
A7: =TRIM(A6) -> Kevin Cookie Company
A9: Concat
A10: Kevin | B10: Cookie | C10: Company
A11: =_xlfn.CONCAT(A10, " ", B10, " ", C10) -> Kevin Cookie Company
A13: &
A14: Kevin | B14: Cookie | C14: Company
A15: =A14&" "&B14&" "&C14 -> Kevin Cookie Company
A17: Text Join
A18: Kevin | B18: Cookie | C18: Company
A19: =_xlfn.TEXTJOIN(" ",TRUE, A18, B18, C18) -> Kevin Cookie Company
A21: Right, Left, Mid
A22: 123 Main Street, 05486
A23: =LEFT(A22, 8) -> 123 Main
A24: Len
A25: Kevin Cookie Company
A26: =LEN(A25) -> 20
A27: Find (case-sensitive) and search (not case-sensitive)
A28: sue@kevincookiecompany.com
A29: =FIND("@",A28) -> 4
A31: Left together with find
A32: =LEFT(A28, FIND("@",A28)-1) -> sue

Sheet Logical Functions
A1: True / False
A2: Kevin Cookie Company | B2: Mrs. Fields | C2: =A2=B2 -> FALSE
A3: 10 | B3: 5 | C3: =A3>B3 -> TRUE
B4: 11 | C4: =B4>A3>B3 -> TRUE
A9: Cookie Name | B9: Cookies Sold | C9: If
A10: Chocolate Chip | B10: 97 | C10: Do we sell more chocolate chip or oatmeal raisin?
A11: Oatmeal Raisin | B11: 150 | C11: =IF(B10>B11,A10,A11) -> Oatmeal Raisin
A12: Sugar Cookie | B12: 150
C13: AND
C14: Does chocolate chip sell more than all other cookies?
C15: =IF(AND(B10>B11,B10>B12),"Yes","No") -> No
C17: OR
C18: Does chocolate chip sell more than oatmeal raisin or sugar?
C19: =IF(OR(B10>B11,B10>B12),"Yes","No") -> No
A21: Cookie Type | B21: Price | C21: Nested If / Ifs
A22: Chocolate Chip | B22: 10 | C22: What is the price of: | E22: Sugar Cookie
A23: Oatmeal Raisin | B23: 8 | C23: =IF(E22=A22,B22,IF(E22=A23,B23,IF(E22=A24,B24,"unknown"))) -> 5
A24: Sugar Cookie | B24: 5 | C24: {=_xlfn.IFS(E22=A22,B22,E22=A23,B23,E22=A24,B24)} -> 5

Sheet Lookup Functions
A1: Cookie Type | B1: Price | C1: Cost | E1: VLOOKUP
A2: Chocolate Chip | B2: 10 | C2: 4 | E2: What is the price of: | F2: Sugar Cookie
A3: Oatmeal Raisin | B3: 8 | C3: 3 | E3: =VLOOKUP(F2,A1:C4,2,FALSE) -> 5
A4: Sugar Cookie | B4: 5 | C4: 2
E5: XLOOKUP
E6: What is the price of: | F6: Chocolate Chip
E7: =_xlfn.XLOOKUP(F6,A:A,B:B) -> 10

Sheet Date & Time
A1: Today
A2: =TODAY() -> 46089
A4: Now
A5: =NOW() -> 46089.137

Sheet Bonus
A1: =5+4 -> 9 | B1: 1
A2: =8-2 -> 6 | B2: 3
A3: =A2+B2 -> 9 | B3: =4+2 -> 6
A4: 3 | B4: =B3+A3 -> 15

Sheet Match & Index
A1: ID | B1: NAME | C1: SCORE | E1: Using Index | F1: JANE SCORE
A2: 1 | B2: JOHN | C2: 85 | E2: =INDEX(C:C,3) -> 98
A3: 2 | B3: JANE | C3: 98
A4: 3 | B4: JOSH | C4: 90 | E4: Using Match | F4: JOHAN POSITION
A5: 4 | B5: JOE | C5: 89 | E5: =MATCH("JOHAN", B:B, 0) -> 6
A6: 5 | B6: JOHAN | C6: 79
E7: Using Index/Match | F7: JOSH SCORE
E8: =INDEX(C:C,MATCH("Josh",B:B,0)) -> 90
